Metadata-Version: 1.1
Name: snimar-thumbnails
Version: 2.0.1
Summary: Generate thumbnails for the SNIMar local catalogues
Home-page: https://bitbucket.org/ipma/snimar_thumbnails
Author: Pedro Dias
Author-email: pedro.dias@ipma.pt
License: MIT
Keywords: snimar,thumbnails
Platform: UNKNOWN
Classifier: Development Status :: 5 - Production/Stable
Classifier: Environment :: Web Environment
Classifier: Intended Audience :: Developers
Classifier: License :: OSI Approved :: MIT License
Classifier: Programming Language :: Python
